digiwise_search_tac/MSRPLUS20231218.xlsx
digiwise_search_tac/__init__.py
digiwise_search_tac/batch_search.py
digiwise_search_tac/digiwise_search_tac.py
digiwise_search_tac-0.1.5.3.dist-info/METADATA
digiwise_search_tac-0.1.5.3.dist-info/WHEEL
digiwise_search_tac-0.1.5.3.dist-info/top_level.txt
digiwise_search_tac-0.1.5.3.dist-info/RECORD
